Metadata-Version: 2.1
Name: probabilita-di-riuscita
Version: 1.0b2
Summary: Gaussian and Binomial distributions
Home-page: UNKNOWN
Author: Roberto Giorgi
Author-email: rjnenjo3@testmail.com
License: UNKNOWN
Platform: UNKNOWN
